atlassian_transfer/__init__.py
Atlassian_Transfer-0.2.0.dist-info/METADATA
Atlassian_Transfer-0.2.0.dist-info/WHEEL
Atlassian_Transfer-0.2.0.dist-info/top_level.txt
Atlassian_Transfer-0.2.0.dist-info/RECORD
