Metadata-Version: 2.1
Name: Atlassian-Transfer
Version: 0.2.0
Summary: An API wrapper for transfer.atlassian.com
Home-page: https://bitbucket.org/dchevell/atlassian-transfer
Author: Dave Chevell
Author-email: chevell@gmail.com
License: MIT
Keywords: requests,transfer,atlassian
Platform: UNKNOWN
Classifier: Programming Language :: Python :: 3
Classifier: License :: OSI Approved :: MIT License
Classifier: Operating System :: OS Independent
Requires-Dist: requests-toolbelt
